[
  {
    "Authors": "Cecen, Ahmet; Dai, Hanjun; Yabansu, Yuksel C; Kalidindi, Surya R; Song, Le;",
    "Title": "Material structure-property linkages using three-dimensional convolutional neural networks",
    "Publication": "Acta Materialia",
    "Volume": 146,
    "Number": "",
    "Pages": "76-84",
    "Year": 2018,
    "Publisher": "Pergamon"
  },
  {
    "Authors": "Surya R. Kalidindi , David B. Brough , Shengyen Li , Ahmet Cecen , Aleksandr L. Blekh , Faical Yannick P. Congo , and Carelyn Campbell",
    "Title": "Role of materials data science and informatics in accelerated materials innovation",
    "Publication": "MRS Bulletin",
    "Volume": "In Press",
    "Number": "",
    "Pages": "",
    "Year": 2016,
    "Publisher": "Materials Research Society"
  },
  {
    "Authors": "Cecen, Ahmet; Fast, Tony; Kalidindi, Surya R;",
    "Title": "Versatile algorithms for the computation of 2-point spatial correlations in quantifying material structure",
    "Publication": "Integrating Materials and Manufacturing Innovation",
    "Volume": 5,
    "Number": 1,
    "Pages": 1,
    "Year": 2016,
    "Publisher": "Springer Berlin Heidelberg"
  },
  {
    "Authors": "Agrawal, Ankit; Deshpande, Parijat D; Cecen, Ahmet; Basavarsu, Gautham P; Choudhary, Alok N; Kalidindi, Surya R;",
    "Title": "Exploration of data science techniques to predict fatigue strength of steel from composition and processing parameters",
    "Publication": "IMMI Journal",
    "Volume": 3,
    "Number": 1,
    "Pages": "1-19",
    "Year": 2014,
    "Publisher": "Springer Berlin Heidelberg"
  }
]